pyksh/__init__.py
pyksh/scda.py
pyksh_oyb-0.1.5.dist-info/licenses/LICENSE
pyksh_oyb-0.1.5.dist-info/METADATA
pyksh_oyb-0.1.5.dist-info/WHEEL
pyksh_oyb-0.1.5.dist-info/top_level.txt
pyksh_oyb-0.1.5.dist-info/RECORD
